spraycharles/__init__.py
spraycharles/__main__.py
spraycharles/commands/__init__.py
spraycharles/commands/analyze.py
spraycharles/commands/gen.py
spraycharles/commands/modules.py
spraycharles/commands/parse.py
spraycharles/commands/spray.py
spraycharles/lib/__init__.py
spraycharles/lib/analyze.py
spraycharles/lib/logger.py
spraycharles/lib/spraycharles.py
spraycharles/lib/utils/__init__.py
spraycharles/lib/utils/notify.py
spraycharles/lib/utils/ntlm_challenger.py
spraycharles/lib/utils/smbstatus.py
spraycharles/lib/utils/sprayresult.py
spraycharles/targets/Adfs.py
spraycharles/targets/Ciscosslvpn.py
spraycharles/targets/Citrix.py
spraycharles/targets/Ntlm.py
spraycharles/targets/Office365.py
spraycharles/targets/Okta.py
spraycharles/targets/Owa.py
spraycharles/targets/Rdg.py
spraycharles/targets/Smb.py
spraycharles/targets/Sonicwall.py
spraycharles/targets/__init__.py
spraycharles/targets/classes/BaseHttpTarget.py
spraycharles-2.0.3.dist-info/LICENSE
spraycharles-2.0.3.dist-info/METADATA
spraycharles-2.0.3.dist-info/WHEEL
spraycharles-2.0.3.dist-info/entry_points.txt
spraycharles-2.0.3.dist-info/RECORD
