Metadata-Version: 2.3
Name: spraycharles
Version: 2.0.3
Summary: Low and slow password spraying tool, designed to spray on an interval over a long period of time.
License: BSD 3-Clause
Author: Matt Creel
Requires-Python: >=3.10,<4.0
Classifier: License :: Other/Proprietary License
Classifier: Programming Language :: Python :: 3
Classifier: Programming Language :: Python :: 3.10
Classifier: Programming Language :: Python :: 3.11
Classifier: Programming Language :: Python :: 3.12
Classifier: Programming Language :: Python :: 3.13
Requires-Dist: click (>=8.0.4,<8.1.0)
Requires-Dist: discord-webhook (>=0.15.0,<0.16.0)
Requires-Dist: impacket (>=0.9.24,<0.10.0)
Requires-Dist: numpy (>=1.22.3,<2.0.0)
Requires-Dist: pymsteams (>=0.2.1,<0.3.0)
Requires-Dist: pyyaml (>=6.0.2,<7.0.0)
Requires-Dist: requests (>=2.27.1,<3.0.0)
Requires-Dist: requests_ntlm (>=1.1.0,<2.0.0)
Requires-Dist: rich (>=12.0.1,<13.0.0)
Requires-Dist: typer (>=0.12.3,<0.13.0)
Requires-Dist: typer-config (>=1.4.0,<2.0.0)
Project-URL: Homepage, https://github.com/Tw1sm/spraycharles
Project-URL: Repository, https://github.com/Tw1sm/spraycharles
